BI/__init__.py
BI/BNN/__init__.py
BI/BNN/activations.py
BI/BNN/bnn.py
BI/BNN/__pycache__/__init__.cpython-312.pyc
BI/BNN/__pycache__/activations.cpython-312.pyc
BI/BNN/__pycache__/bnn.cpython-312.pyc
BI/Data/manip.py
BI/Data/__pycache__/manip.cpython-312.pyc
BI/Diagnostic/Diag.py
BI/Diagnostic/Diag2.py
BI/Diagnostic/__init__.py
BI/Diagnostic/jax_summary.py
BI/Diagnostic/__pycache__/Diag.cpython-312.pyc
BI/Diagnostic/__pycache__/Diag2.cpython-312.pyc
BI/Diagnostic/__pycache__/__init__.cpython-312.pyc
BI/Diagnostic/__pycache__/jax_summary.cpython-312.pyc
BI/ML/KMeans.py
BI/ML/__init__.py
BI/ML/ml.py
BI/ML/__pycache__/KMeans.cpython-312.pyc
BI/ML/__pycache__/__init__.cpython-312.pyc
BI/ML/__pycache__/ml.cpython-312.pyc
BI/Main/__init__.py
BI/Main/main.py
BI/Main/__pycache__/__init__.cpython-312.pyc
BI/Main/__pycache__/main.cpython-312.pyc
BI/Models/DPMM.py
BI/Models/GMM.py
BI/Models/PCA.py
BI/Models/SRM.py
BI/Models/__init__.py
BI/Models/models.py
BI/Models/surv.py
BI/Models/__pycache__/DPMM.cpython-312.pyc
BI/Models/__pycache__/GMM.cpython-312.pyc
BI/Models/__pycache__/PCA.cpython-312.pyc
BI/Models/__pycache__/SRM.cpython-312.pyc
BI/Models/__pycache__/__init__.cpython-312.pyc
BI/Models/__pycache__/dpmm.cpython-312.pyc
BI/Models/__pycache__/gmm.cpython-312.pyc
BI/Models/__pycache__/models.cpython-312.pyc
BI/Models/__pycache__/surv.cpython-312.pyc
BI/NBDA/NBDA.py
BI/NBDA/__init__.py
BI/NBDA/__pycache__/NBDA.cpython-312.pyc
BI/NBDA/__pycache__/__init__.cpython-312.pyc
BI/Network/Net.py
BI/Network/__init__.py
BI/Network/metrics.py
BI/Network/model_effects.py
BI/Network/util.py
BI/Network/__pycache__/Net.cpython-312.pyc
BI/Network/__pycache__/__init__.cpython-312.pyc
BI/Network/__pycache__/metrics.cpython-312.pyc
BI/Network/__pycache__/model_effects.cpython-312.pyc
BI/Network/__pycache__/util.cpython-312.pyc
BI/PostModel/__init__.py
BI/PostModel/to_latex.py
BI/PostModel/__pycache__/__init__.cpython-312.pyc
BI/PostModel/__pycache__/to_latex.cpython-312.pyc
BI/R/BI doc.py
bayesinference-0.0.36.dist-info/licenses/LICENSE
bayesinference-0.0.36.dist-info/METADATA
bayesinference-0.0.36.dist-info/WHEEL
bayesinference-0.0.36.dist-info/top_level.txt
bayesinference-0.0.36.dist-info/RECORD
