Metadata-Version: 2.4
Name: BayesInference
Version: 0.0.36
Summary: A Python package for Bayesian Inference modeling and diagnostics.
Author-email: Sebastian Sosa <bi@s-sosa.com>
License: GPL-3.0-or-later
Project-URL: Homepage, https://github.com/BGN-for-ASNA/BI
Project-URL: Bug Tracker, https://github.com/BGN-for-ASNA/BI/issues
Keywords: python,Bayesian inferences
Classifier: Development Status :: 3 - Alpha
Classifier: Intended Audience :: Education
Classifier: Programming Language :: Python :: 3
Classifier: Operating System :: MacOS :: MacOS X
Classifier: Operating System :: Microsoft :: Windows
Classifier: Operating System :: POSIX :: Linux
Requires-Python: >=3.9
License-File: LICENSE
Requires-Dist: numpyro
Requires-Dist: numpy
Requires-Dist: matplotlib
Requires-Dist: pandas
Requires-Dist: seaborn
Requires-Dist: tensorflow_probability
Requires-Dist: arviz
Requires-Dist: funsor
Requires-Dist: plotly
Provides-Extra: cpu
Requires-Dist: jax; extra == "cpu"
Requires-Dist: jaxlib; extra == "cpu"
Provides-Extra: gpu
Requires-Dist: jax[cuda12_pip]; extra == "gpu"
Dynamic: license-file
